spurt/__init__.py
spurt/_version.py
spurt/graph/__init__.py
spurt/graph/_delaunay.py
spurt/graph/_hop3.py
spurt/graph/_interface.py
spurt/graph/utils.py
spurt/io/__init__.py
spurt/io/_interface.py
spurt/io/_raster.py
spurt/io/_slc_stack.py
spurt/io/_three_d.py
spurt/links/__init__.py
spurt/links/_common.py
spurt/links/_grid_search.py
spurt/links/_interface.py
spurt/mcf/__init__.py
spurt/mcf/_interface.py
spurt/mcf/_ortools.py
spurt/mcf/utils.py
spurt/utils/__init__.py
spurt/utils/_cpu.py
spurt/utils/_logger.py
spurt/utils/_tiling.py
spurt/utils/merge.py
spurt/workflows/__init__.py
spurt/workflows/emcf/__init__.py
spurt/workflows/emcf/__main__.py
spurt/workflows/emcf/_bulk_offset.py
spurt/workflows/emcf/_cli.py
spurt/workflows/emcf/_merge.py
spurt/workflows/emcf/_output.py
spurt/workflows/emcf/_overlap.py
spurt/workflows/emcf/_settings.py
spurt/workflows/emcf/_solver.py
spurt/workflows/emcf/_tiling.py
spurt/workflows/emcf/_unwrap.py
spurt-0.1.1.dist-info/licenses/LICENSE-Apache-2.0
spurt-0.1.1.dist-info/licenses/LICENSE-BSD-3-Clause
spurt-0.1.1.dist-info/METADATA
spurt-0.1.1.dist-info/WHEEL
spurt-0.1.1.dist-info/entry_points.txt
spurt-0.1.1.dist-info/top_level.txt
spurt-0.1.1.dist-info/RECORD
